Workbook

Sheet Summary
B2: BusinessHub — Spec Compliance Audit
B3: Static source-code trace of all 9 modules, 36 user stories and ~90 functional requirements against the running codebase.
B4: Live execution was not possible from this session (no network path to the dev servers, node_modules unreachable) — every finding below is a code citation, not a test run.
B7: Module | C7: Implemented | D7: Partial | E7: Missing | F7: Missing (expected) | G7: Bug | H7: Total
B8: M1 Accounts & Access | C8: =COUNTIFS('Traceability Matrix'!$A:$A,$B8,'Traceability Matrix'!$E:$E,C7) -> 7 | D8: =COUNTIFS('Traceability Matrix'!$A:$A,$B8,'Traceability Matrix'!$E:$E,D7) -> 5 | E8: =COUNTIFS('Traceability Matrix'!$A:$A,$B8,'Traceability Matrix'!$E:$E,E7) -> 0 | F8: =COUNTIFS('Traceability Matrix'!$A:$A,$B8,'Traceability Matrix'!$E:$E,F7) -> 1 | G8: =COUNTIFS('Traceability Matrix'!$A:$A,$B8,'Traceability Matrix'!$E:$E,G7) -> 5 | H8: =SUM(C8:G8) -> 18
B9: M2 CRM | C9: =COUNTIFS('Traceability Matrix'!$A:$A,$B9,'Traceability Matrix'!$E:$E,C7) -> 2 | D9: =COUNTIFS('Traceability Matrix'!$A:$A,$B9,'Traceability Matrix'!$E:$E,D7) -> 9 | E9: =COUNTIFS('Traceability Matrix'!$A:$A,$B9,'Traceability Matrix'!$E:$E,E7) -> 1 | F9: =COUNTIFS('Traceability Matrix'!$A:$A,$B9,'Traceability Matrix'!$E:$E,F7) -> 0 | G9: =COUNTIFS('Traceability Matrix'!$A:$A,$B9,'Traceability Matrix'!$E:$E,G7) -> 2 | H9: =SUM(C9:G9) -> 14
B10: M3 Requests & Cases | C10: =COUNTIFS('Traceability Matrix'!$A:$A,$B10,'Traceability Matrix'!$E:$E,C7) -> 5 | D10: =COUNTIFS('Traceability Matrix'!$A:$A,$B10,'Traceability Matrix'!$E:$E,D7) -> 6 | E10: =COUNTIFS('Traceability Matrix'!$A:$A,$B10,'Traceability Matrix'!$E:$E,E7) -> 2 | F10: =COUNTIFS('Traceability Matrix'!$A:$A,$B10,'Traceability Matrix'!$E:$E,F7) -> 0 | G10: =COUNTIFS('Traceability Matrix'!$A:$A,$B10,'Traceability Matrix'!$E:$E,G7) -> 4 | H10: =SUM(C10:G10) -> 17
B11: M4 Workflow | C11: =COUNTIFS('Traceability Matrix'!$A:$A,$B11,'Traceability Matrix'!$E:$E,C7) -> 4 | D11: =COUNTIFS('Traceability Matrix'!$A:$A,$B11,'Traceability Matrix'!$E:$E,D7) -> 4 | E11: =COUNTIFS('Traceability Matrix'!$A:$A,$B11,'Traceability Matrix'!$E:$E,E7) -> 1 | F11: =COUNTIFS('Traceability Matrix'!$A:$A,$B11,'Traceability Matrix'!$E:$E,F7) -> 0 | G11: =COUNTIFS('Traceability Matrix'!$A:$A,$B11,'Traceability Matrix'!$E:$E,G7) -> 5 | H11: =SUM(C11:G11) -> 14
B12: M5 Documents | C12: =COUNTIFS('Traceability Matrix'!$A:$A,$B12,'Traceability Matrix'!$E:$E,C7) -> 1 | D12: =COUNTIFS('Traceability Matrix'!$A:$A,$B12,'Traceability Matrix'!$E:$E,D7) -> 3 | E12: =COUNTIFS('Traceability Matrix'!$A:$A,$B12,'Traceability Matrix'!$E:$E,E7) -> 3 | F12: =COUNTIFS('Traceability Matrix'!$A:$A,$B12,'Traceability Matrix'!$E:$E,F7) -> 1 | G12: =COUNTIFS('Traceability Matrix'!$A:$A,$B12,'Traceability Matrix'!$E:$E,G7) -> 6 | H12: =SUM(C12:G12) -> 14
B13: M6 Finance | C13: =COUNTIFS('Traceability Matrix'!$A:$A,$B13,'Traceability Matrix'!$E:$E,C7) -> 4 | D13: =COUNTIFS('Traceability Matrix'!$A:$A,$B13,'Traceability Matrix'!$E:$E,D7) -> 8 | E13: =COUNTIFS('Traceability Matrix'!$A:$A,$B13,'Traceability Matrix'!$E:$E,E7) -> 2 | F13: =COUNTIFS('Traceability Matrix'!$A:$A,$B13,'Traceability Matrix'!$E:$E,F7) -> 0 | G13: =COUNTIFS('Traceability Matrix'!$A:$A,$B13,'Traceability Matrix'!$E:$E,G7) -> 4 | H13: =SUM(C13:G13) -> 18
B14: M7 Communication | C14: =COUNTIFS('Traceability Matrix'!$A:$A,$B14,'Traceability Matrix'!$E:$E,C7) -> 2 | D14: =COUNTIFS('Traceability Matrix'!$A:$A,$B14,'Traceability Matrix'!$E:$E,D7) -> 3 | E14: =COUNTIFS('Traceability Matrix'!$A:$A,$B14,'Traceability Matrix'!$E:$E,E7) -> 2 | F14: =COUNTIFS('Traceability Matrix'!$A:$A,$B14,'Traceability Matrix'!$E:$E,F7) -> 0 | G14: =COUNTIFS('Traceability Matrix'!$A:$A,$B14,'Traceability Matrix'!$E:$E,G7) -> 7 | H14: =SUM(C14:G14) -> 14
B15: M8 Reporting | C15: =COUNTIFS('Traceability Matrix'!$A:$A,$B15,'Traceability Matrix'!$E:$E,C7) -> 1 | D15: =COUNTIFS('Traceability Matrix'!$A:$A,$B15,'Traceability Matrix'!$E:$E,D7) -> 5 | E15: =COUNTIFS('Traceability Matrix'!$A:$A,$B15,'Traceability Matrix'!$E:$E,E7) -> 4 | F15: =COUNTIFS('Traceability Matrix'!$A:$A,$B15,'Traceability Matrix'!$E:$E,F7) -> 1 | G15: =COUNTIFS('Traceability Matrix'!$A:$A,$B15,'Traceability Matrix'!$E:$E,G7) -> 2 | H15: =SUM(C15:G15) -> 13
B16: M9 Admin & Audit | C16: =COUNTIFS('Traceability Matrix'!$A:$A,$B16,'Traceability Matrix'!$E:$E,C7) -> 2 | D16: =COUNTIFS('Traceability Matrix'!$A:$A,$B16,'Traceability Matrix'!$E:$E,D7) -> 7 | E16: =COUNTIFS('Traceability Matrix'!$A:$A,$B16,'Traceability Matrix'!$E:$E,E7) -> 2 | F16: =COUNTIFS('Traceability Matrix'!$A:$A,$B16,'Traceability Matrix'!$E:$E,F7) -> 0 | G16: =COUNTIFS('Traceability Matrix'!$A:$A,$B16,'Traceability Matrix'!$E:$E,G7) -> 2 | H16: =SUM(C16:G16) -> 13
B17: TOTAL | C17: =SUM(C8:C16) -> 28 | D17: =SUM(D8:D16) -> 50 | E17: =SUM(E8:E16) -> 17 | F17: =SUM(F8:F16) -> 3 | G17: =SUM(G8:G16) -> 37 | H17: =SUM(H8:H16) -> 135
B20: Highest-priority bugs (Must-have requirement + STATUS: Bug)
B21: FR-6.7 | C21: amountPaid is incremented from a stale pre-transaction read rather than recomputed as SUM(successful payments) inside the transaction — two near-simultaneous payments on one invoice can race and silently under-credit it, contradicting §10.2's "sum recomputed server-side" requirement.
B22: FR-1.11 | C22: None of these methods verify the target membership/user belongs to the caller's own organisation — only the caller's own permission is checked. A partner administrator can deactivate, remove, or change the role of a user in a completely different organisation, and read/update any user's profile by id — a cross-tenant IDOR issue.
B23: FR-1.10 | C23: Read-only is enforced only in cases/finance/workflow modules — no check in tenancy.service.ts at all, so inviteUser/deactivateUser/changeRole/removeMember/createOrganization/createRole/updateRole remain callable during an active impersonation. Also, actions elsewhere during impersonation attribute audit events to the impersonated user, not the real actor — only the start/stop events correctly record both identities.
B24: US-1.3 | C24: Clauses 1 and 3 pass. Clause 2 fails: switchOrganization never calls queryClient.clear()/invalidateQueries, and react-query keys don't include org id — for up to 15s after switching org, a re-mounted component can serve the previous organisation's cached rows under the new context, a real cross-tenant staleness bug.
B25: FR-5.1 | C25: There is no real pre-signed-URL upload path in either backend or frontend — the entire mechanism is mocked/stubbed. Bytes never reach real object storage at all.
B26: FR-8.6 | C26: Any authenticated org member, including a Visitor, can call GET /reports/dashboard directly and receive org-wide case counts and outstanding invoice totals with zero permission check — a report acting exactly as the spec says it must never be.
B27: FR-3.6 | C27: For any CLOSED/ARCHIVED case, an illegal transition returns 403, not the spec-mandated 409 INVALID_TRANSITION. The legitimate CLOSED→ARCHIVED transition is also unreachable in practice — checkNotClosedForMutation blocks it before the transition table is even consulted, and no cron ever invokes it.
B28: US-3.3 | C28: DRAFT→RESOLVED correctly 409s, but any illegal transition from a CLOSED case returns 403 instead — so the general "API returns 409 for any illegal transition" claim is false. History-row-same-transaction and reason-mandatory guards are correct. Concurrency guarantee is also broken: the case is read once outside the transaction and the in-transaction update has no status/version predicate or row lock — two concurrent transition requests can both succeed, each writing its own history row, despite a code comment claiming optimistic concurrency is enforced.
B29: US-4.2 | C29: For a 2-level approval where each level is its own task, approving level 1 immediately transitions the case to APPROVED and notifies the requester even though level 2 is still PENDING and its task stays BLOCKED forever — decideApproval never unblocks the next task on approval (unlike the reject path, which correctly cancels all remaining levels). Clauses 1 (403+PENDING) and 4 (reject cascades) are correct; clauses 2 and 3 (next level opens, final level triggers APPROVED) are not.
B30: FR-1.3 | C30: Two bugs: (1) changeRole lets an admin promote an existing never-enrolled member into Manager/Admin/Super with zero MFA check; (2) inviteUser's check is backwards — a brand-new invitee can never already have mfaSecret set, so every invite into a mandatory-MFA role is unconditionally rejected with 422, pre-empting the actual forced-enrolment-at-first-login mechanism.
B31: US-9.2 | C31: "Available immediately, no restart" — met. "Invalid JSON Schema refused with parse error" — buggy: validation only runs if formSchema arrives as a raw string, but NestJS parses JSON bodies automatically so a normal client sends an object and the check is skipped entirely — any malformed schema silently saves; even when it does run, it only checks JSON syntax, never validates against the JSON Schema meta-schema. "Editing doesn't retroactively invalidate existing cases" — untestable: there is no PUT/PATCH endpoint for case types at all, only creation.
B32: US-9.3 | C32: "See raw response and verdict" — the test is fully mocked, never returns a real provider's response. "Test fails ⇒ cannot be marked active" — buggy: upsertIntegration sets isActive directly from the request body with no check against lastTestResult, so an integration can be marked active without ever passing a test. "Secrets masked except last four characters" — buggy: masking replaces the entire value with a fixed '********' regardless of length, never preserving the last four characters as required.
... B36: FR-2.2 | C36: "Exactly one primary contact enforced by the database" is false — it's enforced only in application code via a transaction+updateMany, and is racy under concurrent writes. The frontend text literally claims DB enforcement (clients/[id]/page.tsx:172).
B38: See the "Traceability Matrix" tab for the full 135-row, item-by-item audit with file:line evidence.

Sheet Traceability Matrix
A1: Module | B1: ID | C1: Type | D1: Priority | E1: Status | F1: Evidence | G1: Notes
A2: M1 Accounts & Access | B2: FR-1.1 | C2: FR | D2: M | E2: Implemented | F2: identity.service.ts:46-97 (register), :124-138 (issueEmailVerification), :158-191 (verifyEmail blocks sign-in until verified) | G2: Registration, verification and password policy (12 chars + breach list, 422) all present; register() returns identical response whether email exists, resisting enumeration.
A3: M1 Accounts & Access | B3: FR-1.2 | C3: FR | D3: M | E3: Implemented | F3: identity.service.ts:328-335 (MFA_REQUIRED challenge on login), :450-507 (verifyMfa) | G3: Matches spec exactly, including 401 MFA_REQUIRED with challengeId.
A4: M1 Accounts & Access | B4: FR-1.3 | C4: FR | D4: M | E4: Bug | F4: tenancy.service.ts:203-214 (inviteUser MFA check), tenancy.service.ts:405-435 (changeRole, no MFA check) | G4: Two bugs: (1) changeRole lets an admin promote an existing never-enrolled member into Manager/Admin/Super with zero MFA check; (2) inviteUser's check is backwards — a brand-new invitee can never already have mfaSecret set, so every invite into a mandatory-MFA role is unconditionally rejected with 422, pre-empting the actual forced-enrolment-at-first-login mechanism.
A5: M1 Accounts & Access | B5: FR-1.4 | C5: FR | D5: M | E5: Implemented | F5: identity.service.ts:203-235 (forgotPassword), :237-270 (resetPassword revokes all sessions in same transaction) | G5: Matches spec; token is single-use and time-limited (1 hour).
A6: M1 Accounts & Access | B6: FR-1.5 | C6: FR | D6: M | E6: Implemented | F6: auth-provider.tsx:261-267 (switchOrganization), lib/api.ts:99-103 (x-organization-id header), auth.guard.ts:84-97 (server re-scopes per request) | G6: Full re-scope without sign-out works end-to-end.
A7: M1 Accounts & Access | B7: FR-1.6 | C7: FR | D7: M | E7: Partial | F7: tenancy.service.ts:169-255 (14-day expiry, email sent), :349-385 (resend/revoke) | G7: Backend resend/revoke logic is correct, but there is no GET list-invitations endpoint and no frontend page references resend or revoke — an administrator has no way to discover a pending invitation to act on it.
A8: M1 Accounts & Access | B8: FR-1.7 | C8: FR | D8: M | E8: Implemented | F8: tenancy.service.ts:485-563 (deactivateUser: DISABLED status, revokes all sessions, unassigns tasks in same transaction) | G8: Mechanics correct (see FR-1.11 for a cross-org scoping caveat on this same endpoint).
A9: M1 Accounts & Access | B9: FR-1.8 | C9: FR | D9: S | E9: Partial | F9: tenancy.service.ts:576-620 (createRole permission-subset check, updateRole SYSTEM_ROLE_IMMUTABLE) | G9: Edit-protection for system roles works server-side; there is no delete-role endpoint at all, and no frontend UI anywhere for creating/editing custom roles — backend-only feature.
A10: M1 Accounts & Access | B10: FR-1.9 | C10: FR | D10: S | E10: Partial | F10: identity.service.ts:594-616 (getSessions/revokeSession), app/(app)/[role]/me/page.tsx:230-286 (session list UI) | G10: Device and revoke work; "last-seen" is actually session creation time, not true last activity; "location" is not implemented — only raw IP shown, no geo/city lookup.
A11: M1 Accounts & Access | B11: FR-1.10 | C11: FR | D11: S | E11: Bug | F11: admin.controller.ts:146-192 (impersonate/stopImpersonation), case-ability.service.ts + cases/finance/workflow services (partial read-only enforcement) | G11: Read-only is enforced only in cases/finance/workflow modules — no check in tenancy.service.ts at all, so inviteUser/deactivateUser/changeRole/removeMember/createOrganization/createRole/updateRole remain callable during an active impersonation. Also, actions elsewhere during impersonation attribute audit events to the impersonated user, not the real actor — only the start/stop events correctly record both identities.
A12: M1 Accounts & Access | B12: FR-1.11 | C12: FR | D12: M | E12: Bug | F12: tenancy.service.ts:389-403 (removeMember), :405-435 (changeRole), :456-482 (getUser/updateUser), :485-488 (deactivateUser) | G12: None of these methods verify the target membership/user belongs to the caller's own organisation — only the caller's own permission is checked. A partner administrator can deactivate, remove, or change the role of a user in a completely different organisation, and read/update any user's profile by id — a cross-tenant IDOR issue.
... A136: M9 Admin & Audit | B136: US-9.3 | C136: US | D136: — | E136: Bug | F136: admin.controller.ts:196-243,201-218; dashboard.tsx (super) is read-only, no config form or test button anywhere in the frontend | G136: "See raw response and verdict" — the test is fully mocked, never returns a real provider's response. "Test fails ⇒ cannot be marked active" — buggy: upsertIntegration sets isActive directly from the request body with no check against lastTestResult, so an integration can be marked active without ever passing a test. "Secrets masked except last four characters" — buggy: masking replaces the entire value with a fixed '********' regardless of length, never preserving the last four characters as required.
